jd_tools/__init__.py
jd_tools/cfg.py
jd_tools/cmd.py
jd_tools/core.py
jd_tools/jd_avatar.py
jd_tools/jd_ip.py
jd_tools/jd_parser.py
jd_tools/logs.py
jd_tools/measure.py
jd_tools/mini_app_template.py
jd_tools/oper_file.py
jd_tools/parser_config.py
jd_tools/rsa_pwd.py
jd_tools/thread_pool.py
jd_tools/tools.py
jd_tools/utils.py
jd_tools/crypto/__init__.py
jd_tools/crypto/aes.py
jd_tools/crypto/gen_key.py
jd_tools/param_check/__init__.py
jd_tools/param_check/errcode.py
jd_tools/param_check/jd_check.py
jd_tools/param_check/validate.py
jd_tools-0.3.0.dist-info/LICENSE
jd_tools-0.3.0.dist-info/METADATA
jd_tools-0.3.0.dist-info/WHEEL
jd_tools-0.3.0.dist-info/top_level.txt
jd_tools-0.3.0.dist-info/RECORD
