Metadata-Version: 2.1
Name: jd-tools
Version: 0.3.0
Summary: JD tools classes/functions, python SDK
Author-email: wxg001 <wxg001@21cn.com>
License: MIT
Project-URL: Homepage, https://pypi.org/project/jd-tools/
Project-URL: Bug Tracker, https://pypi.org/project/jd-tools/
Classifier: Programming Language :: Python :: 3.7
Classifier: Programming Language :: Python :: 3.8
Classifier: Programming Language :: Python :: 3.9
Classifier: Programming Language :: Python :: 3.10
Classifier: License :: OSI Approved :: MIT License
Classifier: Operating System :: OS Independent
Requires-Python: >=3.7
License-File: LICENSE
Requires-Dist: xlrd
Requires-Dist: Pillow
Requires-Dist: qrcode
Requires-Dist: Cryptography
Requires-Dist: requests
